agent_control/__init__.py
agent_control/agents.py
agent_control/client.py
agent_control/control_decorators.py
agent_control/controls.py
agent_control/evaluation.py
agent_control/observability.py
agent_control/policies.py
agent_control/py.typed
agent_control/settings.py
agent_control/tracing.py
agent_control/evaluators/__init__.py
agent_control/evaluators/base.py
agent_control_engine/__init__.py
agent_control_engine/core.py
agent_control_engine/discovery.py
agent_control_engine/evaluators.py
agent_control_engine/py.typed
agent_control_engine/selectors.py
agent_control_models/__init__.py
agent_control_models/agent.py
agent_control_models/base.py
agent_control_models/controls.py
agent_control_models/errors.py
agent_control_models/evaluation.py
agent_control_models/evaluator.py
agent_control_models/health.py
agent_control_models/observability.py
agent_control_models/policy.py
agent_control_models/py.typed
agent_control_models/server.py
agent_control_sdk-3.0.0.dist-info/METADATA
agent_control_sdk-3.0.0.dist-info/WHEEL
agent_control_sdk-3.0.0.dist-info/RECORD
