Metadata-Version: 2.4
Name: agent-control-sdk
Version: 3.0.0
Summary: Python SDK for Agent Control - protect your AI agents with controls
Project-URL: Homepage, https://github.com/yourusername/agent-control
Project-URL: Documentation, https://github.com/yourusername/agent-control#readme
Project-URL: Repository, https://github.com/yourusername/agent-control
Author: Agent Control Team
License: Apache-2.0
Keywords: agent,ai-safety,llm,protection,sdk,security
Classifier: Development Status :: 3 - Alpha
Classifier: Intended Audience :: Developers
Classifier: Programming Language :: Python :: 3
Classifier: Programming Language :: Python :: 3.12
Classifier: Programming Language :: Python :: 3.13
Requires-Python: >=3.12
Requires-Dist: docstring-parser>=0.15
Requires-Dist: google-re2>=1.1
Requires-Dist: httpx>=0.26.0
Requires-Dist: jsonschema>=4.0.0
Requires-Dist: pydantic-settings>=2.0.0
Requires-Dist: pydantic>=2.5.0
Provides-Extra: luna2
Requires-Dist: httpx>=0.24.0; extra == 'luna2'
